Zoom_Utils.py
zoom_utils-0.0.0.dist-info/METADATA
zoom_utils-0.0.0.dist-info/WHEEL
zoom_utils-0.0.0.dist-info/licenses/LICENSE
zoom_utils-0.0.0.dist-info/RECORD
