Metadata-Version: 2.1
Name: Zoom_Utils
Version: 0.0.0
Summary: Zoom utils
Author-email: Sabari Rajan <iamsabarirajan@gmail.com>
License: MIT License
License-File: LICENSE
Keywords: reports,utilities,utils,zoom,zoom reports
Requires-Dist: bs4
Requires-Dist: requests
